Metadata-Version: 2.1
Name: edspdf-mupdf
Version: 0.2.0
Summary: MuPDF extension for EDS-PDF
Author-email: Perceval Wajsburt <perceval.wajsburt-ext@aphp.fr>, Alice Calliger <alice.calliger-ext@aphp.fr>
License:                     GNU AFFERO GENERAL PUBLIC LICENSE
Project-URL: homepage, https://github.com/aphp/edspdf/
Project-URL: repository, https://github.com/aphp/edspdf/
Project-URL: documentation, https://aphp.github.io/edspdf/
Requires-Python: !=3.8.1,<4.0,>3.7.6
Provides-Extra: dev
Provides-Extra: docs
License-File: LICENSE
